PresentMon.exe
pc_perf.py
app/database.py
app/log.py
app/task_handle.py
app/util.py
app/view.py
app/core/monitor.py
app/core/pc_tools.py
test_result/index.html
pc_perf-2.0.0.dist-info/LICENSE
pc_perf-2.0.0.dist-info/METADATA
pc_perf-2.0.0.dist-info/WHEEL
pc_perf-2.0.0.dist-info/top_level.txt
pc_perf-2.0.0.dist-info/RECORD
